csvx/__init__.py
csvx/csv.py
csvx/python2.py
csvx-0.1.1459403998.dist-info/DESCRIPTION.rst
csvx-0.1.1459403998.dist-info/METADATA
csvx-0.1.1459403998.dist-info/RECORD
csvx-0.1.1459403998.dist-info/WHEEL
csvx-0.1.1459403998.dist-info/metadata.json
csvx-0.1.1459403998.dist-info/top_level.txt
