Metadata-Version: 1.1
Name: csvx
Version: 0.1.1459403998
Summary: csvx: painless csv
Home-page: UNKNOWN
Author: Robert Lechte
Author-email: robertlechte@gmail.com
License: UNKNOWN
Platform: UNKNOWN
Classifier: Development Status :: 3 - Alpha
